grokcore.layout-4.1-py3.12-nspkg.pth
grokcore/layout/README.rst
grokcore/layout/__init__.py
grokcore/layout/components.py
grokcore/layout/configure.zcml
grokcore/layout/interfaces.py
grokcore/layout/meta.py
grokcore/layout/meta.zcml
grokcore/layout/tests/__init__.py
grokcore/layout/tests/ftesting.zcml
grokcore/layout/tests/test_functional.py
grokcore/layout/tests/test_package.py
grokcore/layout/tests/test_readme.py
grokcore/layout/tests/errors/__init__.py
grokcore/layout/tests/errors/norenderortemplatelayout.py
grokcore/layout/tests/errors/renderandtemplate.py
grokcore/layout/tests/errors/samecontext.py
grokcore/layout/tests/errors/renderandtemplate_templates/mylayout.pt
grokcore/layout/tests/functional/__init__.py
grokcore/layout/tests/functional/ftesting.zcml
grokcore/layout/tests/functional/layout.py
grokcore/layout/tests/layout/__init__.py
grokcore/layout/tests/layout/layout.py
grokcore/layout/tests/layout/layoutlayers.py
grokcore/layout/tests/layout/no_staticfolder.py
grokcore/layout/tests/layout/selectlayout.py
grokcore/layout/tests/layout/specializedlayout.py
grokcore/layout/tests/layout/staticfolder.py
grokcore/layout/tests/layout/static_fixture/__init__.py
grokcore/layout/tests/layout/static_fixture/simple.py
grokcore/layout/tests/models/__init__.py
grokcore/layout/tests/models/errorviews.py
grokcore/layout/tests/models/page.py
grokcore/layout/tests/models/templates/master.pt
grokcore_layout-4.1.dist-info/LICENSE.txt
grokcore_layout-4.1.dist-info/METADATA
grokcore_layout-4.1.dist-info/WHEEL
grokcore_layout-4.1.dist-info/namespace_packages.txt
grokcore_layout-4.1.dist-info/top_level.txt
grokcore_layout-4.1.dist-info/RECORD
