Metadata-Version: 2.2
Name: grokcore.layout
Version: 4.1
Summary: A layout component package for Grok.
Home-page: https://github.com/zopefoundation/grokcore.layout
Author: Grok Team
Author-email: zope-dev@zope.dev
License: ZPL-2.1
Keywords: grok layout zope3 pagelet theming
Classifier: Development Status :: 6 - Mature
Classifier: Environment :: Web Environment
Classifier: Intended Audience :: Developers
Classifier: License :: OSI Approved :: Zope Public License
Classifier: Programming Language :: Python
Classifier: Programming Language :: Python :: 3
Classifier: Programming Language :: Python :: 3.9
Classifier: Programming Language :: Python :: 3.10
Classifier: Programming Language :: Python :: 3.11
Classifier: Programming Language :: Python :: 3.12
Classifier: Programming Language :: Python :: 3.13
Classifier: Programming Language :: Python :: Implementation
Classifier: Programming Language :: Python :: Implementation :: CPython
Classifier: Programming Language :: Python :: Implementation :: PyPy
Classifier: Framework :: Zope :: 3
Requires-Python: >=3.9
License-File: LICENSE.txt
Requires-Dist: grokcore.component>=2.5
Requires-Dist: grokcore.security>=1.6
Requires-Dist: grokcore.view>=3.0.3
Requires-Dist: martian>=0.14
Requires-Dist: setuptools
Requires-Dist: zope.authentication
Requires-Dist: zope.component>=3.9.1
Requires-Dist: zope.errorview
Requires-Dist: zope.interface
Requires-Dist: zope.publisher
Provides-Extra: test
Requires-Dist: zope.annotation; extra == "test"
Requires-Dist: zope.app.wsgi[test]; extra == "test"
Requires-Dist: zope.container; extra == "test"
Requires-Dist: zope.login; extra == "test"
Requires-Dist: zope.schema; extra == "test"
Requires-Dist: zope.security; extra == "test"
Requires-Dist: zope.session; extra == "test"
Requires-Dist: zope.site; extra == "test"
Requires-Dist: zope.testbrowser; extra == "test"
Requires-Dist: zope.testing; extra == "test"
Requires-Dist: zope.traversing; extra == "test"
Dynamic: author
Dynamic: author-email
Dynamic: classifier
Dynamic: description
Dynamic: home-page
Dynamic: keywords
Dynamic: license
Dynamic: provides-extra
Dynamic: requires-dist
Dynamic: requires-python
Dynamic: summary
